{
  "timestamp": "2025-11-05T20:24:37.010327",
  "saison": 1,
  "runde": 2,
  "series": [
    {
      "a": "Bremerhaven Trident",
      "b": "Schwenningen Sturmflügel",
      "games": [
        {
          "g": 1,
          "home": "Bremerhaven Trident",
          "away": "Schwenningen Sturmflügel",
          "g_home": 2,
          "g_away": 2,
          "winner": "Schwenningen Sturmflügel"
        },
        {
          "g": 2,
          "home": "Bremerhaven Trident",
          "away": "Schwenningen Sturmflügel",
          "g_home": 0,
          "g_away": 2,
          "winner": "Schwenningen Sturmflügel"
        },
        {
          "g": 3,
          "home": "Bremerhaven Trident",
          "away": "Schwenningen Sturmflügel",
          "g_home": 4,
          "g_away": 2,
          "winner": "Bremerhaven Trident"
        },
        {
          "g": 4,
          "home": "Bremerhaven Trident",
          "away": "Schwenningen Sturmflügel",
          "g_home": 0,
          "g_away": 1,
          "winner": "Schwenningen Sturmflügel"
        },
        {
          "g": 5,
          "home": "Bremerhaven Trident",
          "away": "Schwenningen Sturmflügel",
          "g_home": 2,
          "g_away": 3,
          "winner": "Schwenningen Sturmflügel"
        }
      ],
      "result": "1:4",
      "winner": "Schwenningen Sturmflügel"
    },
    {
      "a": "Mannheim Ventus",
      "b": "Ravensburg Zenit Falken",
      "games": [
        {
          "g": 1,
          "home": "Mannheim Ventus",
          "away": "Ravensburg Zenit Falken",
          "g_home": 2,
          "g_away": 3,
          "winner": "Ravensburg Zenit Falken"
        },
        {
          "g": 2,
          "home": "Mannheim Ventus",
          "away": "Ravensburg Zenit Falken",
          "g_home": 0,
          "g_away": 1,
          "winner": "Ravensburg Zenit Falken"
        },
        {
          "g": 3,
          "home": "Mannheim Ventus",
          "away": "Ravensburg Zenit Falken",
          "g_home": 0,
          "g_away": 1,
          "winner": "Ravensburg Zenit Falken"
        },
        {
          "g": 4,
          "home": "Mannheim Ventus",
          "away": "Ravensburg Zenit Falken",
          "g_home": 4,
          "g_away": 3,
          "winner": "Mannheim Ventus"
        },
        {
          "g": 5,
          "home": "Mannheim Ventus",
          "away": "Ravensburg Zenit Falken",
          "g_home": 2,
          "g_away": 3,
          "winner": "Ravensburg Zenit Falken"
        }
      ],
      "result": "1:4",
      "winner": "Ravensburg Zenit Falken"
    }
  ],
  "tabelle_nord": [
    {
      "Team": "Bremerhaven Trident",
      "Points": 34,
      "GF": 44,
      "GA": 34,
      "GD": 10
    },
    {
      "Team": "Whiteout Berlin",
      "Points": 31,
      "GF": 38,
      "GA": 31,
      "GD": 7
    },
    {
      "Team": "Wolfsburg Voltsturm",
      "Points": 29,
      "GF": 37,
      "GA": 30,
      "GD": 7
    },
    {
      "Team": "Kassel Zenit",
      "Points": 26,
      "GF": 38,
      "GA": 37,
      "GD": 1
    },
    {
      "Team": "Krefeld Kernschlag",
      "Points": 24,
      "GF": 37,
      "GA": 33,
      "GD": 4
    },
    {
      "Team": "Köln Blitzhaie",
      "Points": 24,
      "GF": 35,
      "GA": 38,
      "GD": -3
    },
    {
      "Team": "Frankfurt Core",
      "Points": 19,
      "GF": 36,
      "GA": 40,
      "GD": -4
    },
    {
      "Team": "Düsseldorfer Aurora",
      "Points": 19,
      "GF": 27,
      "GA": 35,
      "GD": -8
    },
    {
      "Team": "Iserlohn Miners",
      "Points": 18,
      "GF": 28,
      "GA": 36,
      "GD": -8
    },
    {
      "Team": "Bad Nauheim Devils",
      "Points": 17,
      "GF": 33,
      "GA": 39,
      "GD": -6
    }
  ],
  "tabelle_sued": [
    {
      "Team": "Ravensburg Zenit Falken",
      "Points": 35,
      "GF": 43,
      "GA": 36,
      "GD": 7
    },
    {
      "Team": "Mannheim Ventus",
      "Points": 33,
      "GF": 43,
      "GA": 37,
      "GD": 6
    },
    {
      "Team": "Schwenningen Sturmflügel",
      "Points": 29,
      "GF": 41,
      "GA": 35,
      "GD": 6
    },
    {
      "Team": "Straubing Forest Tigers",
      "Points": 28,
      "GF": 39,
      "GA": 33,
      "GD": 6
    },
    {
      "Team": "Regensburg Pulse",
      "Points": 28,
      "GF": 36,
      "GA": 38,
      "GD": -2
    },
    {
      "Team": "Novadelta Panther",
      "Points": 28,
      "GF": 33,
      "GA": 25,
      "GD": 8
    },
    {
      "Team": "Nürnberg Eistiger",
      "Points": 19,
      "GF": 35,
      "GA": 40,
      "GD": -5
    },
    {
      "Team": "Augsburg Ferox",
      "Points": 18,
      "GF": 35,
      "GA": 40,
      "GD": -5
    },
    {
      "Team": "Landshut Lichtkern",
      "Points": 17,
      "GF": 31,
      "GA": 38,
      "GD": -7
    },
    {
      "Team": "München FluxBullen",
      "Points": 11,
      "GF": 32,
      "GA": 46,
      "GD": -14
    }
  ],
  "top_scorer": [
    {
      "Player": "Luk Yungar",
      "Team": "Ravensburg Zenit Falken",
      "Goals": 7,
      "Assists": 5,
      "Points": 12
    },
    {
      "Player": "Erik Karlov",
      "Team": "Ravensburg Zenit Falken",
      "Goals": 6,
      "Assists": 5,
      "Points": 11
    },
    {
      "Player": "Josh Samanskik",
      "Team": "Straubing Forest Tigers",
      "Goals": 2,
      "Assists": 8,
      "Points": 10
    },
    {
      "Player": "Tay Vausik",
      "Team": "Bad Nauheim Devils",
      "Goals": 3,
      "Assists": 7,
      "Points": 10
    },
    {
      "Player": "Tay Vausik",
      "Team": "Bad Nauheim Devils",
      "Goals": 3,
      "Assists": 7,
      "Points": 10
    },
    {
      "Player": "Nick Lattik",
      "Team": "Ravensburg Zenit Falken",
      "Goals": 2,
      "Assists": 7,
      "Points": 9
    },
    {
      "Player": "Mac Rutkov",
      "Team": "Kassel Zenit",
      "Goals": 5,
      "Assists": 4,
      "Points": 9
    },
    {
      "Player": "Mate Mrazek",
      "Team": "Ravensburg Zenit Falken",
      "Goals": 5,
      "Assists": 4,
      "Points": 9
    },
    {
      "Player": "Ste Majrik",
      "Team": "Schwenningen Sturmflügel",
      "Goals": 3,
      "Assists": 6,
      "Points": 9
    },
    {
      "Player": "Mac Rutkov",
      "Team": "Iserlohn Miners",
      "Goals": 5,
      "Assists": 4,
      "Points": 9
    },
    {
      "Player": "Kris Reichov",
      "Team": "Mannheim Ventus",
      "Goals": 4,
      "Assists": 4,
      "Points": 8
    },
    {
      "Player": "Mir Höffvik",
      "Team": "Schwenningen Sturmflügel",
      "Goals": 5,
      "Assists": 3,
      "Points": 8
    },
    {
      "Player": "Rya Macinnov",
      "Team": "Mannheim Ventus",
      "Goals": 4,
      "Assists": 4,
      "Points": 8
    },
    {
      "Player": "Marc Michaelov",
      "Team": "Mannheim Ventus",
      "Goals": 6,
      "Assists": 2,
      "Points": 8
    },
    {
      "Player": "Eli Pulsen",
      "Team": "Novadelta Panther",
      "Goals": 1,
      "Assists": 7,
      "Points": 8
    },
    {
      "Player": "Ansel Gergov",
      "Team": "Ravensburg Zenit Falken",
      "Goals": 5,
      "Assists": 3,
      "Points": 8
    },
    {
      "Player": "Hun Garlov",
      "Team": "Kassel Zenit",
      "Goals": 5,
      "Assists": 3,
      "Points": 8
    },
    {
      "Player": "Zac Dybowik",
      "Team": "Krefeld Kernschlag",
      "Goals": 3,
      "Assists": 5,
      "Points": 8
    },
    {
      "Player": "Mar Erkov",
      "Team": "Bad Nauheim Devils",
      "Goals": 3,
      "Assists": 5,
      "Points": 8
    },
    {
      "Player": "Mark Vikstad",
      "Team": "Bremerhaven Trident",
      "Goals": 7,
      "Assists": 1,
      "Points": 8
    }
  ]
}